aegs/__init__.py
aegs/gensim_model
aegs/lstm_model
aegs-0.0.6.dist-info/METADATA
aegs-0.0.6.dist-info/WHEEL
aegs-0.0.6.dist-info/top_level.txt
aegs-0.0.6.dist-info/RECORD
