Metadata-Version: 2.1
Name: aegs
Version: 0.0.6
Summary: model for aegs.
Home-page: https://github.com/RishabhBhatnagar/mlp
Author: Rishabh Bhatnagar
Author-email: bhatnagarrishabh4@gmail.com
License: UNKNOWN
Platform: UNKNOWN
Classifier: Programming Language :: Python :: 3
Classifier: License :: OSI Approved :: MIT License
Classifier: Operating System :: OS Independent
